pysteamcmdwrapper/SteamCMD.py
pysteamcmdwrapper/SteamCMD_command.py
pysteamcmdwrapper/__init__.py
pysteamcmdwrapper/exceptions.py
py_steamcmd_wrapper-1.1.1.dist-info/LICENSE.md
py_steamcmd_wrapper-1.1.1.dist-info/METADATA
py_steamcmd_wrapper-1.1.1.dist-info/WHEEL
py_steamcmd_wrapper-1.1.1.dist-info/top_level.txt
py_steamcmd_wrapper-1.1.1.dist-info/RECORD
