Metadata-Version: 2.1
Name: py-steamcmd-wrapper
Version: 1.1.1
Summary: Python wrapper for SteamCMD
Home-page: https://github.com/wmellema/pysteamcmdwrapper
Author: Wouter Mellema
Author-email: info@woutermellema.nl
License: UNKNOWN
Platform: UNKNOWN
Classifier: Programming Language :: Python :: 3
Classifier: License :: OSI Approved :: MIT License
Classifier: Operating System :: OS Independent
Classifier: License :: OSI Approved :: GNU General Public License v3 (GPLv3)
Requires-Python: >=3.6
License-File: LICENSE.md
Requires-Dist: requests
